shellcrafter/__init__.py
shellcrafter/cli.py
shellcrafter/find_gadgets.py
shellcrafter/keyst_api.py
shellcrafter/peutils.py
shellcrafter/shellcode_procedure_generator.py
shellcrafter-1.1.7.dist-info/METADATA
shellcrafter-1.1.7.dist-info/WHEEL
shellcrafter-1.1.7.dist-info/entry_points.txt
shellcrafter-1.1.7.dist-info/top_level.txt
shellcrafter-1.1.7.dist-info/RECORD
