Metadata-Version: 2.1
Name: shellcrafter
Version: 1.1.7
Summary: A package containing scripts for developing and generating shellcode
Home-page: https://github.com/totekuh/shellcrafter
Author: totekuh
Author-email: totekuh@protonmail.com
Project-URL: Bug Reports, https://github.com/totekuh/shellcrafter/issues
Project-URL: Source, https://github.com/totekuh/shellcrafter
Requires-Dist: numpy
Requires-Dist: keystone-engine
Requires-Dist: termcolor
Requires-Dist: rich
Requires-Dist: ropper
Requires-Dist: capstone
Requires-Dist: typer
Requires-Dist: pefile
